april.py
setup.py
april.egg-info/PKG-INFO
april.egg-info/SOURCES.txt
april.egg-info/dependency_links.txt
april.egg-info/entry_points.txt
april.egg-info/top_level.txt