Metadata-Version: 1.1
Name: april
Version: 2.0.1
Summary: simplified obj
Home-page: https://github.com/cosven/april
Author: Cosven
Author-email: cosven.yin@gmail.com
License: UNKNOWN
Keywords: struct,model
Platform: UNKNOWN
Classifier: Programming Language :: Python :: 2.7
Classifier: Programming Language :: Python :: 3.4
Classifier: Programming Language :: Python :: 3.5
